mellisuga/__init__.py
mellisuga/api.py
mellisuga/errors.py
mellisuga/mellisuga.py
mellisuga/request.py
mellisuga/response.py
mellisuga-0.0.6.dist-info/METADATA
mellisuga-0.0.6.dist-info/WHEEL
mellisuga-0.0.6.dist-info/top_level.txt
mellisuga-0.0.6.dist-info/RECORD
