Metadata-Version: 2.1
Name: mellisuga
Version: 0.0.6
Summary: AWS Lambda Microframework
Home-page: https://gitlab.com/Zuendel/mellisuga
Author: Johannes Zuendel
Author-email: jozuendel@gmail.com
License: Apache License 2.0
Keywords: mellisuga aws labmda microframework websocket
Platform: UNKNOWN
